opentoken/__init__.py
opentoken/_ciphersuite.py
opentoken/_token.py
opentoken/_utils.py
opentoken/opentoken.py
opentoken-2.2.0.dist-info/LICENSE
opentoken-2.2.0.dist-info/METADATA
opentoken-2.2.0.dist-info/WHEEL
opentoken-2.2.0.dist-info/top_level.txt
opentoken-2.2.0.dist-info/RECORD
