Metadata-Version: 2.1
Name: opentoken
Version: 2.2.0
Summary: OpenToken support for python.
Home-page: https://github.com/yoonjesung/opentoken-python
Author: Jason Yoon
License: MIT
Platform: UNKNOWN
Classifier: Programming Language :: Python :: 3
Classifier: License :: OSI Approved :: MIT License
Classifier: Operating System :: OS Independent
Classifier: Intended Audience :: Developers
Classifier: Programming Language :: Python :: 3.5
Classifier: Programming Language :: Python :: 3.6
Classifier: Programming Language :: Python :: 3.7
Classifier: Programming Language :: Python :: 3.8
Requires-Python: >=3.5
Requires-Dist: pycryptodomex (==3.9.7)
Requires-Dist: python-dateutil (==2.8.1)
